tello_sdk_remake-0.2.0.dist-info/METADATA
tello_sdk_remake-0.2.0.dist-info/WHEEL
tello_sdk/__init__.py
tello_sdk/__init__.pyi
tello_sdk/py.typed
tello_sdk/tello_sdk.cpython-38-x86_64-linux-gnu.so
tello_sdk_remake-0.2.0.dist-info/RECORD
